Workbook

Sheet Início
A1: PAINEL FINANCEIRO · Gê
A2: Tudo que você tem, deve, ganha e planeja — num lugar só. Se atualiza sozinho a partir dos Lançamentos.
B4: Mês de referência | C4: =TEXT(TODAY(),"YYYY-MM") | E4: ↑ troque essa célula pra ver outro mês (ex: 2026-03)
B6: ENTROU NO MÊS | E6: SAIU NO MÊS | H6: SALDO DO MÊS
B7: =SUMIFS('Lançamentos'!$F:$F,'Lançamentos'!$A:$A,">="&DATE(VALUE(LEFT($C$4,4)),VALUE(RIGHT($C$4,2)),1),'Lançamentos'!$A:$A,"<"&DATE(VALUE(LEFT($C$4,4)),VALUE(RIGHT($C$4,2))+1,1),'Lançamentos'!$C:$C,"Entrada") | E7: =SUMIFS('Lançamentos'!$F:$F,'Lançamentos'!$A:$A,">="&DATE(VALUE(LEFT($C$4,4)),VALUE(RIGHT($C$4,2)),1),'Lançamentos'!$A:$A,"<"&DATE(VALUE(LEFT($C$4,4)),VALUE(RIGHT($C$4,2))+1,1),'Lançamentos'!$C:$C,"Saída") | H7: =B7-E7
B10: PESSOAL · saldo | E10: CLEAN TOUCH · saldo | H10: INTERNET · saldo
B11: =SUMIFS('Lançamentos'!$F:$F,'Lançamentos'!$A:$A,">="&DATE(VALUE(LEFT($C$4,4)),VALUE(RIGHT($C$4,2)),1),'Lançamentos'!$A:$A,"<"&DATE(VALUE(LEFT($C$4,4)),VALUE(RIGHT($C$4,2))+1,1),'Lançamentos'!$B:$B,"Pessoal",'Lançamentos'!$C:$C,"Entrada")-SUMIFS('Lançamentos'!$F:$F,'Lançamentos'!$A:$A,">="&DATE(VALUE(LEFT($C$4,4)),VALUE(RIGHT($C$4,2)),1),'Lançamentos'!$A:$A,"<"&DATE(VALUE(LEFT($C$4,4)),VALUE(RIGHT($C$4,2))+1,1),'Lançamentos'!$B:$B,"Pessoal",'Lançamentos'!$C:$C,"Saída") | E11: =SUMIFS('Lançamentos'!$F:$F,'Lançamentos'!$A:$A,">="&DATE(VALUE(LEFT($C$4,4)),VALUE(RIGHT($C$4,2)),1),'Lançamentos'!$A:$A,"<"&DATE(VALUE(LEFT($C$4,4)),VALUE(RIGHT($C$4,2))+1,1),'Lançamentos'!$B:$B,"Clean Touch",'Lançamentos'!$C:$C,"Entrada")-SUMIFS('Lançamentos'!$F:$F,'Lançamentos'!$A:$A,">="&DATE(VALUE(LEFT($C$4,4)),VALUE(RIGHT($C$4,2)),1),'Lançamentos'!$A:$A,"<"&DATE(VALUE(LEFT($C$4,4)),VALUE(RIGHT($C$4,2))+1,1),'Lançamentos'!$B:$B,"Clean Touch",'Lançamentos'!$C:$C,"Saída") | H11: =SUMIFS('Lançamentos'!$F:$F,'Lançamentos'!$A:$A,">="&DATE(VALUE(LEFT($C$4,4)),VALUE(RIGHT($C$4,2)),1),'Lançamentos'!$A:$A,"<"&DATE(VALUE(LEFT($C$4,4)),VALUE(RIGHT($C$4,2))+1,1),'Lançamentos'!$B:$B,"Internet",'Lançamentos'!$C:$C,"Entrada")-SUMIFS('Lançamentos'!$F:$F,'Lançamentos'!$A:$A,">="&DATE(VALUE(LEFT($C$4,4)),VALUE(RIGHT($C$4,2)),1),'Lançamentos'!$A:$A,"<"&DATE(VALUE(LEFT($C$4,4)),VALUE(RIGHT($C$4,2))+1,1),'Lançamentos'!$B:$B,"Internet",'Lançamentos'!$C:$C,"Saída")
B14: PATRIMÔNIO LÍQUIDO | E14: VOCÊ DEVE HOJE | H14: PARCELAS POR MÊS
B15: ='Patrimônio'!E29 | E15: ='Cartões e Dívidas'!H33 | H15: ='Cartões e Dívidas'!H34
B18: ASSINATURAS / MÊS | E18: ASSINATURAS / ANO | H18: ESTRATÉGIAS ATIVAS
B19: =Assinaturas!G36 | E19: =Assinaturas!H36 | H19: =Estratégias!H31
A21: COMO USAR · leia uma vez, depois nunca mais
B22: 1. Todo dia (2 min): abra a aba Lançamentos e registre o que entrou e o que saiu. Só isso.
B23: 2. Toda semana: olhe a coluna Status — o que está 'Pendente' e já venceu vira problema.
B24: 3. Dia 1 do mês: atualize os valores da aba Patrimônio e preencha uma linha do Snapshot.
B25: 4. Dia 1 do mês: revise Estratégias — o que avançou, o que morreu, qual é a próxima ação.
B26: 5. A cada 3 meses: abra Assinaturas e cancele o que não usou. Olhe a coluna 'Custo no ano'.
B28: As abas Início, Resumo Mensal, Cartões e Dívidas se calculam sozinhas — não digite nelas.
B29: As três frentes são Pessoal, Clean Touch e Internet. Sempre preencha a coluna Frente: é ela que separa tudo.

Sheet Lançamentos
A1: LANÇAMENTOS · tudo que entra e tudo que sai
A2: Uma linha por movimento. É a única aba onde você digita todo dia. Todo o resto se calcula a partir daqui.
A4: Data | B4: Frente | C4: Tipo | D4: Categoria | E4: Descrição | F4: Valor | G4: Forma de pagamento | H4: Cartão | I4: Parcela | J4: Status

Sheet Resumo Mensal
A1: RESUMO MENSAL · 2026
A2: Não digite nada aqui. Tudo vem dos Lançamentos. Se um número parece errado, o erro está lá.
A4: Mês | B4: Pessoal entra | C4: Pessoal sai | D4: Pessoal saldo | E4: Clean Touch entra | F4: Clean Touch sai | G4: Clean Touch saldo | H4: Internet entra | I4: Internet sai | J4: Internet saldo | K4: TOTAL entra | L4: TOTAL sai | M4: SALDO DO MÊS | N4: ACUMULADO
A5: 2026-01 | B5: =SUMIFS('Lançamentos'!$F:$F,'Lançamentos'!$A:$A,">="&DATE(VALUE(LEFT($A5,4)),VALUE(RIGHT($A5,2)),1),'Lançamentos'!$A:$A,"<"&DATE(VALUE(LEFT($A5,4)),VALUE(RIGHT($A5,2))+1,1),'Lançamentos'!$B:$B,"Pessoal",'Lançamentos'!$C:$C,"Entrada") | C5: =SUMIFS('Lançamentos'!$F:$F,'Lançamentos'!$A:$A,">="&DATE(VALUE(LEFT($A5,4)),VALUE(RIGHT($A5,2)),1),'Lançamentos'!$A:$A,"<"&DATE(VALUE(LEFT($A5,4)),VALUE(RIGHT($A5,2))+1,1),'Lançamentos'!$B:$B,"Pessoal",'Lançamentos'!$C:$C,"Saída") | D5: =B5-C5 | E5: =SUMIFS('Lançamentos'!$F:$F,'Lançamentos'!$A:$A,">="&DATE(VALUE(LEFT($A5,4)),VALUE(RIGHT($A5,2)),1),'Lançamentos'!$A:$A,"<"&DATE(VALUE(LEFT($A5,4)),VALUE(RIGHT($A5,2))+1,1),'Lançamentos'!$B:$B,"Clean Touch",'Lançamentos'!$C:$C,"Entrada") | F5: =SUMIFS('Lançamentos'!$F:$F,'Lançamentos'!$A:$A,">="&DATE(VALUE(LEFT($A5,4)),VALUE(RIGHT($A5,2)),1),'Lançamentos'!$A:$A,"<"&DATE(VALUE(LEFT($A5,4)),VALUE(RIGHT($A5,2))+1,1),'Lançamentos'!$B:$B,"Clean Touch",'Lançamentos'!$C:$C,"Saída") | G5: =E5-F5 | H5: =SUMIFS('Lançamentos'!$F:$F,'Lançamentos'!$A:$A,">="&DATE(VALUE(LEFT($A5,4)),VALUE(RIGHT($A5,2)),1),'Lançamentos'!$A:$A,"<"&DATE(VALUE(LEFT($A5,4)),VALUE(RIGHT($A5,2))+1,1),'Lançamentos'!$B:$B,"Internet",'Lançamentos'!$C:$C,"Entrada") | I5: =SUMIFS('Lançamentos'!$F:$F,'Lançamentos'!$A:$A,">="&DATE(VALUE(LEFT($A5,4)),VALUE(RIGHT($A5,2)),1),'Lançamentos'!$A:$A,"<"&DATE(VALUE(LEFT($A5,4)),VALUE(RIGHT($A5,2))+1,1),'Lançamentos'!$B:$B,"Internet",'Lançamentos'!$C:$C,"Saída") | J5: =H5-I5 | K5: =B5+E5+H5 | L5: =C5+F5+I5 | M5: =K5-L5 | N5: =M5
A6: 2026-02 | B6: =SUMIFS('Lançamentos'!$F:$F,'Lançamentos'!$A:$A,">="&DATE(VALUE(LEFT($A6,4)),VALUE(RIGHT($A6,2)),1),'Lançamentos'!$A:$A,"<"&DATE(VALUE(LEFT($A6,4)),VALUE(RIGHT($A6,2))+1,1),'Lançamentos'!$B:$B,"Pessoal",'Lançamentos'!$C:$C,"Entrada") | C6: =SUMIFS('Lançamentos'!$F:$F,'Lançamentos'!$A:$A,">="&DATE(VALUE(LEFT($A6,4)),VALUE(RIGHT($A6,2)),1),'Lançamentos'!$A:$A,"<"&DATE(VALUE(LEFT($A6,4)),VALUE(RIGHT($A6,2))+1,1),'Lançamentos'!$B:$B,"Pessoal",'Lançamentos'!$C:$C,"Saída") | D6: =B6-C6 | E6: =SUMIFS('Lançamentos'!$F:$F,'Lançamentos'!$A:$A,">="&DATE(VALUE(LEFT($A6,4)),VALUE(RIGHT($A6,2)),1),'Lançamentos'!$A:$A,"<"&DATE(VALUE(LEFT($A6,4)),VALUE(RIGHT($A6,2))+1,1),'Lançamentos'!$B:$B,"Clean Touch",'Lançamentos'!$C:$C,"Entrada") | F6: =SUMIFS('Lançamentos'!$F:$F,'Lançamentos'!$A:$A,">="&DATE(VALUE(LEFT($A6,4)),VALUE(RIGHT($A6,2)),1),'Lançamentos'!$A:$A,"<"&DATE(VALUE(LEFT($A6,4)),VALUE(RIGHT($A6,2))+1,1),'Lançamentos'!$B:$B,"Clean Touch",'Lançamentos'!$C:$C,"Saída") | G6: =E6-F6 | H6: =SUMIFS('Lançamentos'!$F:$F,'Lançamentos'!$A:$A,">="&DATE(VALUE(LEFT($A6,4)),VALUE(RIGHT($A6,2)),1),'Lançamentos'!$A:$A,"<"&DATE(VALUE(LEFT($A6,4)),VALUE(RIGHT($A6,2))+1,1),'Lançamentos'!$B:$B,"Internet",'Lançamentos'!$C:$C,"Entrada") | I6: =SUMIFS('Lançamentos'!$F:$F,'Lançamentos'!$A:$A,">="&DATE(VALUE(LEFT($A6,4)),VALUE(RIGHT($A6,2)),1),'Lançamentos'!$A:$A,"<"&DATE(VALUE(LEFT($A6,4)),VALUE(RIGHT($A6,2))+1,1),'Lançamentos'!$B:$B,"Internet",'Lançamentos'!$C:$C,"Saída") | J6: =H6-I6 | K6: =B6+E6+H6 | L6: =C6+F6+I6 | M6: =K6-L6 | N6: =N5+M6
A7: 2026-03 | B7: =SUMIFS('Lançamentos'!$F:$F,'Lançamentos'!$A:$A,">="&DATE(VALUE(LEFT($A7,4)),VALUE(RIGHT($A7,2)),1),'Lançamentos'!$A:$A,"<"&DATE(VALUE(LEFT($A7,4)),VALUE(RIGHT($A7,2))+1,1),'Lançamentos'!$B:$B,"Pessoal",'Lançamentos'!$C:$C,"Entrada") | C7: =SUMIFS('Lançamentos'!$F:$F,'Lançamentos'!$A:$A,">="&DATE(VALUE(LEFT($A7,4)),VALUE(RIGHT($A7,2)),1),'Lançamentos'!$A:$A,"<"&DATE(VALUE(LEFT($A7,4)),VALUE(RIGHT($A7,2))+1,1),'Lançamentos'!$B:$B,"Pessoal",'Lançamentos'!$C:$C,"Saída") | D7: =B7-C7 | E7: =SUMIFS('Lançamentos'!$F:$F,'Lançamentos'!$A:$A,">="&DATE(VALUE(LEFT($A7,4)),VALUE(RIGHT($A7,2)),1),'Lançamentos'!$A:$A,"<"&DATE(VALUE(LEFT($A7,4)),VALUE(RIGHT($A7,2))+1,1),'Lançamentos'!$B:$B,"Clean Touch",'Lançamentos'!$C:$C,"Entrada") | F7: =SUMIFS('Lançamentos'!$F:$F,'Lançamentos'!$A:$A,">="&DATE(VALUE(LEFT($A7,4)),VALUE(RIGHT($A7,2)),1),'Lançamentos'!$A:$A,"<"&DATE(VALUE(LEFT($A7,4)),VALUE(RIGHT($A7,2))+1,1),'Lançamentos'!$B:$B,"Clean Touch",'Lançamentos'!$C:$C,"Saída") | G7: =E7-F7 | H7: =SUMIFS('Lançamentos'!$F:$F,'Lançamentos'!$A:$A,">="&DATE(VALUE(LEFT($A7,4)),VALUE(RIGHT($A7,2)),1),'Lançamentos'!$A:$A,"<"&DATE(VALUE(LEFT($A7,4)),VALUE(RIGHT($A7,2))+1,1),'Lançamentos'!$B:$B,"Internet",'Lançamentos'!$C:$C,"Entrada") | I7: =SUMIFS('Lançamentos'!$F:$F,'Lançamentos'!$A:$A,">="&DATE(VALUE(LEFT($A7,4)),VALUE(RIGHT($A7,2)),1),'Lançamentos'!$A:$A,"<"&DATE(VALUE(LEFT($A7,4)),VALUE(RIGHT($A7,2))+1,1),'Lançamentos'!$B:$B,"Internet",'Lançamentos'!$C:$C,"Saída") | J7: =H7-I7 | K7: =B7+E7+H7 | L7: =C7+F7+I7 | M7: =K7-L7 | N7: =N6+M7
A8: 2026-04 | B8: =SUMIFS('Lançamentos'!$F:$F,'Lançamentos'!$A:$A,">="&DATE(VALUE(LEFT($A8,4)),VALUE(RIGHT($A8,2)),1),'Lançamentos'!$A:$A,"<"&DATE(VALUE(LEFT($A8,4)),VALUE(RIGHT($A8,2))+1,1),'Lançamentos'!$B:$B,"Pessoal",'Lançamentos'!$C:$C,"Entrada") | C8: =SUMIFS('Lançamentos'!$F:$F,'Lançamentos'!$A:$A,">="&DATE(VALUE(LEFT($A8,4)),VALUE(RIGHT($A8,2)),1),'Lançamentos'!$A:$A,"<"&DATE(VALUE(LEFT($A8,4)),VALUE(RIGHT($A8,2))+1,1),'Lançamentos'!$B:$B,"Pessoal",'Lançamentos'!$C:$C,"Saída") | D8: =B8-C8 | E8: =SUMIFS('Lançamentos'!$F:$F,'Lançamentos'!$A:$A,">="&DATE(VALUE(LEFT($A8,4)),VALUE(RIGHT($A8,2)),1),'Lançamentos'!$A:$A,"<"&DATE(VALUE(LEFT($A8,4)),VALUE(RIGHT($A8,2))+1,1),'Lançamentos'!$B:$B,"Clean Touch",'Lançamentos'!$C:$C,"Entrada") | F8: =SUMIFS('Lançamentos'!$F:$F,'Lançamentos'!$A:$A,">="&DATE(VALUE(LEFT($A8,4)),VALUE(RIGHT($A8,2)),1),'Lançamentos'!$A:$A,"<"&DATE(VALUE(LEFT($A8,4)),VALUE(RIGHT($A8,2))+1,1),'Lançamentos'!$B:$B,"Clean Touch",'Lançamentos'!$C:$C,"Saída") | G8: =E8-F8 | H8: =SUMIFS('Lançamentos'!$F:$F,'Lançamentos'!$A:$A,">="&DATE(VALUE(LEFT($A8,4)),VALUE(RIGHT($A8,2)),1),'Lançamentos'!$A:$A,"<"&DATE(VALUE(LEFT($A8,4)),VALUE(RIGHT($A8,2))+1,1),'Lançamentos'!$B:$B,"Internet",'Lançamentos'!$C:$C,"Entrada") | I8: =SUMIFS('Lançamentos'!$F:$F,'Lançamentos'!$A:$A,">="&DATE(VALUE(LEFT($A8,4)),VALUE(RIGHT($A8,2)),1),'Lançamentos'!$A:$A,"<"&DATE(VALUE(LEFT($A8,4)),VALUE(RIGHT($A8,2))+1,1),'Lançamentos'!$B:$B,"Internet",'Lançamentos'!$C:$C,"Saída") | J8: =H8-I8 | K8: =B8+E8+H8 | L8: =C8+F8+I8 | M8: =K8-L8 | N8: =N7+M8
A9: 2026-05 | B9: =SUMIFS('Lançamentos'!$F:$F,'Lançamentos'!$A:$A,">="&DATE(VALUE(LEFT($A9,4)),VALUE(RIGHT($A9,2)),1),'Lançamentos'!$A:$A,"<"&DATE(VALUE(LEFT($A9,4)),VALUE(RIGHT($A9,2))+1,1),'Lançamentos'!$B:$B,"Pessoal",'Lançamentos'!$C:$C,"Entrada") | C9: =SUMIFS('Lançamentos'!$F:$F,'Lançamentos'!$A:$A,">="&DATE(VALUE(LEFT($A9,4)),VALUE(RIGHT($A9,2)),1),'Lançamentos'!$A:$A,"<"&DATE(VALUE(LEFT($A9,4)),VALUE(RIGHT($A9,2))+1,1),'Lançamentos'!$B:$B,"Pessoal",'Lançamentos'!$C:$C,"Saída") | D9: =B9-C9 | E9: =SUMIFS('Lançamentos'!$F:$F,'Lançamentos'!$A:$A,">="&DATE(VALUE(LEFT($A9,4)),VALUE(RIGHT($A9,2)),1),'Lançamentos'!$A:$A,"<"&DATE(VALUE(LEFT($A9,4)),VALUE(RIGHT($A9,2))+1,1),'Lançamentos'!$B:$B,"Clean Touch",'Lançamentos'!$C:$C,"Entrada") | F9: =SUMIFS('Lançamentos'!$F:$F,'Lançamentos'!$A:$A,">="&DATE(VALUE(LEFT($A9,4)),VALUE(RIGHT($A9,2)),1),'Lançamentos'!$A:$A,"<"&DATE(VALUE(LEFT($A9,4)),VALUE(RIGHT($A9,2))+1,1),'Lançamentos'!$B:$B,"Clean Touch",'Lançamentos'!$C:$C,"Saída") | G9: =E9-F9 | H9: =SUMIFS('Lançamentos'!$F:$F,'Lançamentos'!$A:$A,">="&DATE(VALUE(LEFT($A9,4)),VALUE(RIGHT($A9,2)),1),'Lançamentos'!$A:$A,"<"&DATE(VALUE(LEFT($A9,4)),VALUE(RIGHT($A9,2))+1,1),'Lançamentos'!$B:$B,"Internet",'Lançamentos'!$C:$C,"Entrada") | I9: =SUMIFS('Lançamentos'!$F:$F,'Lançamentos'!$A:$A,">="&DATE(VALUE(LEFT($A9,4)),VALUE(RIGHT($A9,2)),1),'Lançamentos'!$A:$A,"<"&DATE(VALUE(LEFT($A9,4)),VALUE(RIGHT($A9,2))+1,1),'Lançamentos'!$B:$B,"Internet",'Lançamentos'!$C:$C,"Saída") | J9: =H9-I9 | K9: =B9+E9+H9 | L9: =C9+F9+I9 | M9: =K9-L9 | N9: =N8+M9
A10: 2026-06 | B10: =SUMIFS('Lançamentos'!$F:$F,'Lançamentos'!$A:$A,">="&DATE(VALUE(LEFT($A10,4)),VALUE(RIGHT($A10,2)),1),'Lançamentos'!$A:$A,"<"&DATE(VALUE(LEFT($A10,4)),VALUE(RIGHT($A10,2))+1,1),'Lançamentos'!$B:$B,"Pessoal",'Lançamentos'!$C:$C,"Entrada") | C10: =SUMIFS('Lançamentos'!$F:$F,'Lançamentos'!$A:$A,">="&DATE(VALUE(LEFT($A10,4)),VALUE(RIGHT($A10,2)),1),'Lançamentos'!$A:$A,"<"&DATE(VALUE(LEFT($A10,4)),VALUE(RIGHT($A10,2))+1,1),'Lançamentos'!$B:$B,"Pessoal",'Lançamentos'!$C:$C,"Saída") | D10: =B10-C10 | E10: =SUMIFS('Lançamentos'!$F:$F,'Lançamentos'!$A:$A,">="&DATE(VALUE(LEFT($A10,4)),VALUE(RIGHT($A10,2)),1),'Lançamentos'!$A:$A,"<"&DATE(VALUE(LEFT($A10,4)),VALUE(RIGHT($A10,2))+1,1),'Lançamentos'!$B:$B,"Clean Touch",'Lançamentos'!$C:$C,"Entrada") | F10: =SUMIFS('Lançamentos'!$F:$F,'Lançamentos'!$A:$A,">="&DATE(VALUE(LEFT($A10,4)),VALUE(RIGHT($A10,2)),1),'Lançamentos'!$A:$A,"<"&DATE(VALUE(LEFT($A10,4)),VALUE(RIGHT($A10,2))+1,1),'Lançamentos'!$B:$B,"Clean Touch",'Lançamentos'!$C:$C,"Saída") | G10: =E10-F10 | H10: =SUMIFS('Lançamentos'!$F:$F,'Lançamentos'!$A:$A,">="&DATE(VALUE(LEFT($A10,4)),VALUE(RIGHT($A10,2)),1),'Lançamentos'!$A:$A,"<"&DATE(VALUE(LEFT($A10,4)),VALUE(RIGHT($A10,2))+1,1),'Lançamentos'!$B:$B,"Internet",'Lançamentos'!$C:$C,"Entrada") | I10: =SUMIFS('Lançamentos'!$F:$F,'Lançamentos'!$A:$A,">="&DATE(VALUE(LEFT($A10,4)),VALUE(RIGHT($A10,2)),1),'Lançamentos'!$A:$A,"<"&DATE(VALUE(LEFT($A10,4)),VALUE(RIGHT($A10,2))+1,1),'Lançamentos'!$B:$B,"Internet",'Lançamentos'!$C:$C,"Saída") | J10: =H10-I10 | K10: =B10+E10+H10 | L10: =C10+F10+I10 | M10: =K10-L10 | N10: =N9+M10
A11: 2026-07 | B11: =SUMIFS('Lançamentos'!$F:$F,'Lançamentos'!$A:$A,">="&DATE(VALUE(LEFT($A11,4)),VALUE(RIGHT($A11,2)),1),'Lançamentos'!$A:$A,"<"&DATE(VALUE(LEFT($A11,4)),VALUE(RIGHT($A11,2))+1,1),'Lançamentos'!$B:$B,"Pessoal",'Lançamentos'!$C:$C,"Entrada") | C11: =SUMIFS('Lançamentos'!$F:$F,'Lançamentos'!$A:$A,">="&DATE(VALUE(LEFT($A11,4)),VALUE(RIGHT($A11,2)),1),'Lançamentos'!$A:$A,"<"&DATE(VALUE(LEFT($A11,4)),VALUE(RIGHT($A11,2))+1,1),'Lançamentos'!$B:$B,"Pessoal",'Lançamentos'!$C:$C,"Saída") | D11: =B11-C11 | E11: =SUMIFS('Lançamentos'!$F:$F,'Lançamentos'!$A:$A,">="&DATE(VALUE(LEFT($A11,4)),VALUE(RIGHT($A11,2)),1),'Lançamentos'!$A:$A,"<"&DATE(VALUE(LEFT($A11,4)),VALUE(RIGHT($A11,2))+1,1),'Lançamentos'!$B:$B,"Clean Touch",'Lançamentos'!$C:$C,"Entrada") | F11: =SUMIFS('Lançamentos'!$F:$F,'Lançamentos'!$A:$A,">="&DATE(VALUE(LEFT($A11,4)),VALUE(RIGHT($A11,2)),1),'Lançamentos'!$A:$A,"<"&DATE(VALUE(LEFT($A11,4)),VALUE(RIGHT($A11,2))+1,1),'Lançamentos'!$B:$B,"Clean Touch",'Lançamentos'!$C:$C,"Saída") | G11: =E11-F11 | H11: =SUMIFS('Lançamentos'!$F:$F,'Lançamentos'!$A:$A,">="&DATE(VALUE(LEFT($A11,4)),VALUE(RIGHT($A11,2)),1),'Lançamentos'!$A:$A,"<"&DATE(VALUE(LEFT($A11,4)),VALUE(RIGHT($A11,2))+1,1),'Lançamentos'!$B:$B,"Internet",'Lançamentos'!$C:$C,"Entrada") | I11: =SUMIFS('Lançamentos'!$F:$F,'Lançamentos'!$A:$A,">="&DATE(VALUE(LEFT($A11,4)),VALUE(RIGHT($A11,2)),1),'Lançamentos'!$A:$A,"<"&DATE(VALUE(LEFT($A11,4)),VALUE(RIGHT($A11,2))+1,1),'Lançamentos'!$B:$B,"Internet",'Lançamentos'!$C:$C,"Saída") | J11: =H11-I11 | K11: =B11+E11+H11 | L11: =C11+F11+I11 | M11: =K11-L11 | N11: =N10+M11
A12: 2026-08 | B12: =SUMIFS('Lançamentos'!$F:$F,'Lançamentos'!$A:$A,">="&DATE(VALUE(LEFT($A12,4)),VALUE(RIGHT($A12,2)),1),'Lançamentos'!$A:$A,"<"&DATE(VALUE(LEFT($A12,4)),VALUE(RIGHT($A12,2))+1,1),'Lançamentos'!$B:$B,"Pessoal",'Lançamentos'!$C:$C,"Entrada") | C12: =SUMIFS('Lançamentos'!$F:$F,'Lançamentos'!$A:$A,">="&DATE(VALUE(LEFT($A12,4)),VALUE(RIGHT($A12,2)),1),'Lançamentos'!$A:$A,"<"&DATE(VALUE(LEFT($A12,4)),VALUE(RIGHT($A12,2))+1,1),'Lançamentos'!$B:$B,"Pessoal",'Lançamentos'!$C:$C,"Saída") | D12: =B12-C12 | E12: =SUMIFS('Lançamentos'!$F:$F,'Lançamentos'!$A:$A,">="&DATE(VALUE(LEFT($A12,4)),VALUE(RIGHT($A12,2)),1),'Lançamentos'!$A:$A,"<"&DATE(VALUE(LEFT($A12,4)),VALUE(RIGHT($A12,2))+1,1),'Lançamentos'!$B:$B,"Clean Touch",'Lançamentos'!$C:$C,"Entrada") | F12: =SUMIFS('Lançamentos'!$F:$F,'Lançamentos'!$A:$A,">="&DATE(VALUE(LEFT($A12,4)),VALUE(RIGHT($A12,2)),1),'Lançamentos'!$A:$A,"<"&DATE(VALUE(LEFT($A12,4)),VALUE(RIGHT($A12,2))+1,1),'Lançamentos'!$B:$B,"Clean Touch",'Lançamentos'!$C:$C,"Saída") | G12: =E12-F12 | H12: =SUMIFS('Lançamentos'!$F:$F,'Lançamentos'!$A:$A,">="&DATE(VALUE(LEFT($A12,4)),VALUE(RIGHT($A12,2)),1),'Lançamentos'!$A:$A,"<"&DATE(VALUE(LEFT($A12,4)),VALUE(RIGHT($A12,2))+1,1),'Lançamentos'!$B:$B,"Internet",'Lançamentos'!$C:$C,"Entrada") | I12: =SUMIFS('Lançamentos'!$F:$F,'Lançamentos'!$A:$A,">="&DATE(VALUE(LEFT($A12,4)),VALUE(RIGHT($A12,2)),1),'Lançamentos'!$A:$A,"<"&DATE(VALUE(LEFT($A12,4)),VALUE(RIGHT($A12,2))+1,1),'Lançamentos'!$B:$B,"Internet",'Lançamentos'!$C:$C,"Saída") | J12: =H12-I12 | K12: =B12+E12+H12 | L12: =C12+F12+I12 | M12: =K12-L12 | N12: =N11+M12
A13: 2026-09 | B13: =SUMIFS('Lançamentos'!$F:$F,'Lançamentos'!$A:$A,">="&DATE(VALUE(LEFT($A13,4)),VALUE(RIGHT($A13,2)),1),'Lançamentos'!$A:$A,"<"&DATE(VALUE(LEFT($A13,4)),VALUE(RIGHT($A13,2))+1,1),'Lançamentos'!$B:$B,"Pessoal",'Lançamentos'!$C:$C,"Entrada") | C13: =SUMIFS('Lançamentos'!$F:$F,'Lançamentos'!$A:$A,">="&DATE(VALUE(LEFT($A13,4)),VALUE(RIGHT($A13,2)),1),'Lançamentos'!$A:$A,"<"&DATE(VALUE(LEFT($A13,4)),VALUE(RIGHT($A13,2))+1,1),'Lançamentos'!$B:$B,"Pessoal",'Lançamentos'!$C:$C,"Saída") | D13: =B13-C13 | E13: =SUMIFS('Lançamentos'!$F:$F,'Lançamentos'!$A:$A,">="&DATE(VALUE(LEFT($A13,4)),VALUE(RIGHT($A13,2)),1),'Lançamentos'!$A:$A,"<"&DATE(VALUE(LEFT($A13,4)),VALUE(RIGHT($A13,2))+1,1),'Lançamentos'!$B:$B,"Clean Touch",'Lançamentos'!$C:$C,"Entrada") | F13: =SUMIFS('Lançamentos'!$F:$F,'Lançamentos'!$A:$A,">="&DATE(VALUE(LEFT($A13,4)),VALUE(RIGHT($A13,2)),1),'Lançamentos'!$A:$A,"<"&DATE(VALUE(LEFT($A13,4)),VALUE(RIGHT($A13,2))+1,1),'Lançamentos'!$B:$B,"Clean Touch",'Lançamentos'!$C:$C,"Saída") | G13: =E13-F13 | H13: =SUMIFS('Lançamentos'!$F:$F,'Lançamentos'!$A:$A,">="&DATE(VALUE(LEFT($A13,4)),VALUE(RIGHT($A13,2)),1),'Lançamentos'!$A:$A,"<"&DATE(VALUE(LEFT($A13,4)),VALUE(RIGHT($A13,2))+1,1),'Lançamentos'!$B:$B,"Internet",'Lançamentos'!$C:$C,"Entrada") | I13: =SUMIFS('Lançamentos'!$F:$F,'Lançamentos'!$A:$A,">="&DATE(VALUE(LEFT($A13,4)),VALUE(RIGHT($A13,2)),1),'Lançamentos'!$A:$A,"<"&DATE(VALUE(LEFT($A13,4)),VALUE(RIGHT($A13,2))+1,1),'Lançamentos'!$B:$B,"Internet",'Lançamentos'!$C:$C,"Saída") | J13: =H13-I13 | K13: =B13+E13+H13 | L13: =C13+F13+I13 | M13: =K13-L13 | N13: =N12+M13
A14: 2026-10 | B14: =SUMIFS('Lançamentos'!$F:$F,'Lançamentos'!$A:$A,">="&DATE(VALUE(LEFT($A14,4)),VALUE(RIGHT($A14,2)),1),'Lançamentos'!$A:$A,"<"&DATE(VALUE(LEFT($A14,4)),VALUE(RIGHT($A14,2))+1,1),'Lançamentos'!$B:$B,"Pessoal",'Lançamentos'!$C:$C,"Entrada") | C14: =SUMIFS('Lançamentos'!$F:$F,'Lançamentos'!$A:$A,">="&DATE(VALUE(LEFT($A14,4)),VALUE(RIGHT($A14,2)),1),'Lançamentos'!$A:$A,"<"&DATE(VALUE(LEFT($A14,4)),VALUE(RIGHT($A14,2))+1,1),'Lançamentos'!$B:$B,"Pessoal",'Lançamentos'!$C:$C,"Saída") | D14: =B14-C14 | E14: =SUMIFS('Lançamentos'!$F:$F,'Lançamentos'!$A:$A,">="&DATE(VALUE(LEFT($A14,4)),VALUE(RIGHT($A14,2)),1),'Lançamentos'!$A:$A,"<"&DATE(VALUE(LEFT($A14,4)),VALUE(RIGHT($A14,2))+1,1),'Lançamentos'!$B:$B,"Clean Touch",'Lançamentos'!$C:$C,"Entrada") | F14: =SUMIFS('Lançamentos'!$F:$F,'Lançamentos'!$A:$A,">="&DATE(VALUE(LEFT($A14,4)),VALUE(RIGHT($A14,2)),1),'Lançamentos'!$A:$A,"<"&DATE(VALUE(LEFT($A14,4)),VALUE(RIGHT($A14,2))+1,1),'Lançamentos'!$B:$B,"Clean Touch",'Lançamentos'!$C:$C,"Saída") | G14: =E14-F14 | H14: =SUMIFS('Lançamentos'!$F:$F,'Lançamentos'!$A:$A,">="&DATE(VALUE(LEFT($A14,4)),VALUE(RIGHT($A14,2)),1),'Lançamentos'!$A:$A,"<"&DATE(VALUE(LEFT($A14,4)),VALUE(RIGHT($A14,2))+1,1),'Lançamentos'!$B:$B,"Internet",'Lançamentos'!$C:$C,"Entrada") | I14: =SUMIFS('Lançamentos'!$F:$F,'Lançamentos'!$A:$A,">="&DATE(VALUE(LEFT($A14,4)),VALUE(RIGHT($A14,2)),1),'Lançamentos'!$A:$A,"<"&DATE(VALUE(LEFT($A14,4)),VALUE(RIGHT($A14,2))+1,1),'Lançamentos'!$B:$B,"Internet",'Lançamentos'!$C:$C,"Saída") | J14: =H14-I14 | K14: =B14+E14+H14 | L14: =C14+F14+I14 | M14: =K14-L14 | N14: =N13+M14
A15: 2026-11 | B15: =SUMIFS('Lançamentos'!$F:$F,'Lançamentos'!$A:$A,">="&DATE(VALUE(LEFT($A15,4)),VALUE(RIGHT($A15,2)),1),'Lançamentos'!$A:$A,"<"&DATE(VALUE(LEFT($A15,4)),VALUE(RIGHT($A15,2))+1,1),'Lançamentos'!$B:$B,"Pessoal",'Lançamentos'!$C:$C,"Entrada") | C15: =SUMIFS('Lançamentos'!$F:$F,'Lançamentos'!$A:$A,">="&DATE(VALUE(LEFT($A15,4)),VALUE(RIGHT($A15,2)),1),'Lançamentos'!$A:$A,"<"&DATE(VALUE(LEFT($A15,4)),VALUE(RIGHT($A15,2))+1,1),'Lançamentos'!$B:$B,"Pessoal",'Lançamentos'!$C:$C,"Saída") | D15: =B15-C15 | E15: =SUMIFS('Lançamentos'!$F:$F,'Lançamentos'!$A:$A,">="&DATE(VALUE(LEFT($A15,4)),VALUE(RIGHT($A15,2)),1),'Lançamentos'!$A:$A,"<"&DATE(VALUE(LEFT($A15,4)),VALUE(RIGHT($A15,2))+1,1),'Lançamentos'!$B:$B,"Clean Touch",'Lançamentos'!$C:$C,"Entrada") | F15: =SUMIFS('Lançamentos'!$F:$F,'Lançamentos'!$A:$A,">="&DATE(VALUE(LEFT($A15,4)),VALUE(RIGHT($A15,2)),1),'Lançamentos'!$A:$A,"<"&DATE(VALUE(LEFT($A15,4)),VALUE(RIGHT($A15,2))+1,1),'Lançamentos'!$B:$B,"Clean Touch",'Lançamentos'!$C:$C,"Saída") | G15: =E15-F15 | H15: =SUMIFS('Lançamentos'!$F:$F,'Lançamentos'!$A:$A,">="&DATE(VALUE(LEFT($A15,4)),VALUE(RIGHT($A15,2)),1),'Lançamentos'!$A:$A,"<"&DATE(VALUE(LEFT($A15,4)),VALUE(RIGHT($A15,2))+1,1),'Lançamentos'!$B:$B,"Internet",'Lançamentos'!$C:$C,"Entrada") | I15: =SUMIFS('Lançamentos'!$F:$F,'Lançamentos'!$A:$A,">="&DATE(VALUE(LEFT($A15,4)),VALUE(RIGHT($A15,2)),1),'Lançamentos'!$A:$A,"<"&DATE(VALUE(LEFT($A15,4)),VALUE(RIGHT($A15,2))+1,1),'Lançamentos'!$B:$B,"Internet",'Lançamentos'!$C:$C,"Saída") | J15: =H15-I15 | K15: =B15+E15+H15 | L15: =C15+F15+I15 | M15: =K15-L15 | N15: =N14+M15
A16: 2026-12 | B16: =SUMIFS('Lançamentos'!$F:$F,'Lançamentos'!$A:$A,">="&DATE(VALUE(LEFT($A16,4)),VALUE(RIGHT($A16,2)),1),'Lançamentos'!$A:$A,"<"&DATE(VALUE(LEFT($A16,4)),VALUE(RIGHT($A16,2))+1,1),'Lançamentos'!$B:$B,"Pessoal",'Lançamentos'!$C:$C,"Entrada") | C16: =SUMIFS('Lançamentos'!$F:$F,'Lançamentos'!$A:$A,">="&DATE(VALUE(LEFT($A16,4)),VALUE(RIGHT($A16,2)),1),'Lançamentos'!$A:$A,"<"&DATE(VALUE(LEFT($A16,4)),VALUE(RIGHT($A16,2))+1,1),'Lançamentos'!$B:$B,"Pessoal",'Lançamentos'!$C:$C,"Saída") | D16: =B16-C16 | E16: =SUMIFS('Lançamentos'!$F:$F,'Lançamentos'!$A:$A,">="&DATE(VALUE(LEFT($A16,4)),VALUE(RIGHT($A16,2)),1),'Lançamentos'!$A:$A,"<"&DATE(VALUE(LEFT($A16,4)),VALUE(RIGHT($A16,2))+1,1),'Lançamentos'!$B:$B,"Clean Touch",'Lançamentos'!$C:$C,"Entrada") | F16: =SUMIFS('Lançamentos'!$F:$F,'Lançamentos'!$A:$A,">="&DATE(VALUE(LEFT($A16,4)),VALUE(RIGHT($A16,2)),1),'Lançamentos'!$A:$A,"<"&DATE(VALUE(LEFT($A16,4)),VALUE(RIGHT($A16,2))+1,1),'Lançamentos'!$B:$B,"Clean Touch",'Lançamentos'!$C:$C,"Saída") | G16: =E16-F16 | H16: =SUMIFS('Lançamentos'!$F:$F,'Lançamentos'!$A:$A,">="&DATE(VALUE(LEFT($A16,4)),VALUE(RIGHT($A16,2)),1),'Lançamentos'!$A:$A,"<"&DATE(VALUE(LEFT($A16,4)),VALUE(RIGHT($A16,2))+1,1),'Lançamentos'!$B:$B,"Internet",'Lançamentos'!$C:$C,"Entrada") | I16: =SUMIFS('Lançamentos'!$F:$F,'Lançamentos'!$A:$A,">="&DATE(VALUE(LEFT($A16,4)),VALUE(RIGHT($A16,2)),1),'Lançamentos'!$A:$A,"<"&DATE(VALUE(LEFT($A16,4)),VALUE(RIGHT($A16,2))+1,1),'Lançamentos'!$B:$B,"Internet",'Lançamentos'!$C:$C,"Saída") | J16: =H16-I16 | K16: =B16+E16+H16 | L16: =C16+F16+I16 | M16: =K16-L16 | N16: =N15+M16
A17: TOTAL 2026 | B17: =SUM(B5:B16) | C17: =SUM(C5:C16) | D17: =SUM(D5:D16) | E17: =SUM(E5:E16) | F17: =SUM(F5:F16) | G17: =SUM(G5:G16) | H17: =SUM(H5:H16) | I17: =SUM(I5:I16) | ... M17: =SUM(M5:M16) | N17: =N16

Sheet Cartões e Dívidas
A1: CARTÕES E DÍVIDAS · quanto você deve e até quando
A2: Preencha as colunas claras. Fatura do mês, saldo devedor e data de quitação se calculam sozinhos.
A4: CARTÕES
A5: Cartão | B5: Bandeira | C5: Frente | D5: Limite | E5: Fecha dia | F5: Vence dia | G5: Fatura do mês | H5: Limite usado | I5: Anuidade | J5: Ativo? | K5: Observação
G6: =IF($A6="","",SUMIFS('Lançamentos'!$F:$F,'Lançamentos'!$H:$H,$A6,'Lançamentos'!$A:$A,">="&DATE(YEAR(TODAY()),MONTH(TODAY()),1),'Lançamentos'!$A:$A,"<"&DATE(YEAR(TODAY()),MONTH(TODAY())+1,1),'Lançamentos'!$C:$C,"Saída")) | H6: =IF(N($D6)=0,"",$G6/$D6)
G7: =IF($A7="","",SUMIFS('Lançamentos'!$F:$F,'Lançamentos'!$H:$H,$A7,'Lançamentos'!$A:$A,">="&DATE(YEAR(TODAY()),MONTH(TODAY()),1),'Lançamentos'!$A:$A,"<"&DATE(YEAR(TODAY()),MONTH(TODAY())+1,1),'Lançamentos'!$C:$C,"Saída")) | H7: =IF(N($D7)=0,"",$G7/$D7)
G8: =IF($A8="","",SUMIFS('Lançamentos'!$F:$F,'Lançamentos'!$H:$H,$A8,'Lançamentos'!$A:$A,">="&DATE(YEAR(TODAY()),MONTH(TODAY()),1),'Lançamentos'!$A:$A,"<"&DATE(YEAR(TODAY()),MONTH(TODAY())+1,1),'Lançamentos'!$C:$C,"Saída")) | H8: =IF(N($D8)=0,"",$G8/$D8)
G9: =IF($A9="","",SUMIFS('Lançamentos'!$F:$F,'Lançamentos'!$H:$H,$A9,'Lançamentos'!$A:$A,">="&DATE(YEAR(TODAY()),MONTH(TODAY()),1),'Lançamentos'!$A:$A,"<"&DATE(YEAR(TODAY()),MONTH(TODAY())+1,1),'Lançamentos'!$C:$C,"Saída")) | H9: =IF(N($D9)=0,"",$G9/$D9)
G10: =IF($A10="","",SUMIFS('Lançamentos'!$F:$F,'Lançamentos'!$H:$H,$A10,'Lançamentos'!$A:$A,">="&DATE(YEAR(TODAY()),MONTH(TODAY()),1),'Lançamentos'!$A:$A,"<"&DATE(YEAR(TODAY()),MONTH(TODAY())+1,1),'Lançamentos'!$C:$C,"Saída")) | H10: =IF(N($D10)=0,"",$G10/$D10)
G11: =IF($A11="","",SUMIFS('Lançamentos'!$F:$F,'Lançamentos'!$H:$H,$A11,'Lançamentos'!$A:$A,">="&DATE(YEAR(TODAY()),MONTH(TODAY()),1),'Lançamentos'!$A:$A,"<"&DATE(YEAR(TODAY()),MONTH(TODAY())+1,1),'Lançamentos'!$C:$C,"Saída")) | H11: =IF(N($D11)=0,"",$G11/$D11)
G12: =IF($A12="","",SUMIFS('Lançamentos'!$F:$F,'Lançamentos'!$H:$H,$A12,'Lançamentos'!$A:$A,">="&DATE(YEAR(TODAY()),MONTH(TODAY()),1),'Lançamentos'!$A:$A,"<"&DATE(YEAR(TODAY()),MONTH(TODAY())+1,1),'Lançamentos'!$C:$C,"Saída")) | H12: =IF(N($D12)=0,"",$G12/$D12)
G13: =IF($A13="","",SUMIFS('Lançamentos'!$F:$F,'Lançamentos'!$H:$H,$A13,'Lançamentos'!$A:$A,">="&DATE(YEAR(TODAY()),MONTH(TODAY()),1),'Lançamentos'!$A:$A,"<"&DATE(YEAR(TODAY()),MONTH(TODAY())+1,1),'Lançamentos'!$C:$C,"Saída")) | H13: =IF(N($D13)=0,"",$G13/$D13)
A15: DÍVIDAS, PARCELAMENTOS E FINANCIAMENTOS
A16: Descrição | B16: Credor | C16: Frente | D16: Valor total | E16: Parcela mensal | F16: Parcelas pagas | G16: Total de parcelas | H16: Saldo devedor | I16: 1ª parcela | J16: Quitação prevista | K16: Status
H17: =IF($E17="","",MAX(0,($G17-$F17)*$E17)) | J17: =IF(OR($I17="",$G17=""),"",EDATE($I17,$G17-1))
H18: =IF($E18="","",MAX(0,($G18-$F18)*$E18)) | J18: =IF(OR($I18="",$G18=""),"",EDATE($I18,$G18-1))
H19: =IF($E19="","",MAX(0,($G19-$F19)*$E19)) | J19: =IF(OR($I19="",$G19=""),"",EDATE($I19,$G19-1))
H20: =IF($E20="","",MAX(0,($G20-$F20)*$E20)) | J20: =IF(OR($I20="",$G20=""),"",EDATE($I20,$G20-1))
H21: =IF($E21="","",MAX(0,($G21-$F21)*$E21)) | J21: =IF(OR($I21="",$G21=""),"",EDATE($I21,$G21-1))
H22: =IF($E22="","",MAX(0,($G22-$F22)*$E22)) | J22: =IF(OR($I22="",$G22=""),"",EDATE($I22,$G22-1))
H23: =IF($E23="","",MAX(0,($G23-$F23)*$E23)) | J23: =IF(OR($I23="",$G23=""),"",EDATE($I23,$G23-1))
H24: =IF($E24="","",MAX(0,($G24-$F24)*$E24)) | J24: =IF(OR($I24="",$G24=""),"",EDATE($I24,$G24-1))
H25: =IF($E25="","",MAX(0,($G25-$F25)*$E25)) | J25: =IF(OR($I25="",$G25=""),"",EDATE($I25,$G25-1))
H26: =IF($E26="","",MAX(0,($G26-$F26)*$E26)) | J26: =IF(OR($I26="",$G26=""),"",EDATE($I26,$G26-1))
H27: =IF($E27="","",MAX(0,($G27-$F27)*$E27)) | J27: =IF(OR($I27="",$G27=""),"",EDATE($I27,$G27-1))
H28: =IF($E28="","",MAX(0,($G28-$F28)*$E28)) | J28: =IF(OR($I28="",$G28=""),"",EDATE($I28,$G28-1))
... H31: =IF($E31="","",MAX(0,($G31-$F31)*$E31)) | J31: =IF(OR($I31="",$G31=""),"",EDATE($I31,$G31-1))
A33: TOTAL QUE VOCÊ DEVE HOJE | H33: =SUM(H17:H31)
A34: COMPROMETIDO POR MÊS (parcelas ativas) | H34: =SUMIFS(E17:E31,K17:K31,"Ativo")

Sheet Patrimônio
A1: PATRIMÔNIO · o que é seu de verdade
A2: Ativos menos dívidas. Atualize os valores uma vez por mês e registre a linha do Snapshot.
A4: O QUE VOCÊ TEM
A5: Item | B5: Tipo | C5: Instituição | D5: Frente | E5: Valor atual | F5: Rende? | G5: Rendimento a.a. | H5: Observação
A27: TOTAL DE ATIVOS | E27: =SUM(E6:E25)
A28: TOTAL DE DÍVIDAS | E28: ='Cartões e Dívidas'!H33
A29: PATRIMÔNIO LÍQUIDO | E29: =E27-E28
A31: SNAPSHOT MENSAL · registre no dia 1 de cada mês
A32: Mês | B32: Ativos | C32: Dívidas | D32: Patrimônio líquido | E32: Variação | F32: Variação % | H32: O que mudou
D33: =IF($B33="","",$B33-$C33)
D34: =IF($B34="","",$B34-$C34) | E34: =IF(OR($D34="",$D33=""),"",$D34-$D33) | F34: =IF(N($D33)=0,"",$E34/ABS($D33))
D35: =IF($B35="","",$B35-$C35) | E35: =IF(OR($D35="",$D34=""),"",$D35-$D34) | F35: =IF(N($D34)=0,"",$E35/ABS($D34))
D36: =IF($B36="","",$B36-$C36) | E36: =IF(OR($D36="",$D35=""),"",$D36-$D35) | F36: =IF(N($D35)=0,"",$E36/ABS($D35))
D37: =IF($B37="","",$B37-$C37) | E37: =IF(OR($D37="",$D36=""),"",$D37-$D36) | F37: =IF(N($D36)=0,"",$E37/ABS($D36))
D38: =IF($B38="","",$B38-$C38) | E38: =IF(OR($D38="",$D37=""),"",$D38-$D37) | F38: =IF(N($D37)=0,"",$E38/ABS($D37))
D39: =IF($B39="","",$B39-$C39) | E39: =IF(OR($D39="",$D38=""),"",$D39-$D38) | F39: =IF(N($D38)=0,"",$E39/ABS($D38))
D40: =IF($B40="","",$B40-$C40) | E40: =IF(OR($D40="",$D39=""),"",$D40-$D39) | F40: =IF(N($D39)=0,"",$E40/ABS($D39))
D41: =IF($B41="","",$B41-$C41) | E41: =IF(OR($D41="",$D40=""),"",$D41-$D40) | F41: =IF(N($D40)=0,"",$E41/ABS($D40))
D42: =IF($B42="","",$B42-$C42) | E42: =IF(OR($D42="",$D41=""),"",$D42-$D41) | F42: =IF(N($D41)=0,"",$E42/ABS($D41))
D43: =IF($B43="","",$B43-$C43) | E43: =IF(OR($D43="",$D42=""),"",$D43-$D42) | F43: =IF(N($D42)=0,"",$E43/ABS($D42))
D44: =IF($B44="","",$B44-$C44) | E44: =IF(OR($D44="",$D43=""),"",$D44-$D43) | F44: =IF(N($D43)=0,"",$E44/ABS($D43))
D45: =IF($B45="","",$B45-$C45) | E45: =IF(OR($D45="",$D44=""),"",$D45-$D44) | F45: =IF(N($D44)=0,"",$E45/ABS($D44))
... D56: =IF($B56="","",$B56-$C56) | E56: =IF(OR($D56="",$D55=""),"",$D56-$D55) | F56: =IF(N($D55)=0,"",$E56/ABS($D55))

Sheet Metas
A1: METAS · pra onde o dinheiro está indo de propósito
A2: Coloque o alvo e o prazo. A planilha te diz quanto precisa guardar por mês pra chegar lá.
A4: Meta | B4: Frente | C4: Por que importa | D4: Valor alvo | E4: Já guardado | F4: Falta | G4: % concluído | H4: Prazo | I4: Meses restantes | J4: Guardar por mês
F5: =IF($D5="","",MAX(0,$D5-$E5)) | G5: =IF(N($D5)=0,"",MIN(1,$E5/$D5)) | I5: =IF($H5="","",MAX(0,DATEDIF(TODAY(),$H5,"M"))) | J5: =IF(N($I5)=0,"",$F5/$I5)
F6: =IF($D6="","",MAX(0,$D6-$E6)) | G6: =IF(N($D6)=0,"",MIN(1,$E6/$D6)) | I6: =IF($H6="","",MAX(0,DATEDIF(TODAY(),$H6,"M"))) | J6: =IF(N($I6)=0,"",$F6/$I6)
F7: =IF($D7="","",MAX(0,$D7-$E7)) | G7: =IF(N($D7)=0,"",MIN(1,$E7/$D7)) | I7: =IF($H7="","",MAX(0,DATEDIF(TODAY(),$H7,"M"))) | J7: =IF(N($I7)=0,"",$F7/$I7)
F8: =IF($D8="","",MAX(0,$D8-$E8)) | G8: =IF(N($D8)=0,"",MIN(1,$E8/$D8)) | I8: =IF($H8="","",MAX(0,DATEDIF(TODAY(),$H8,"M"))) | J8: =IF(N($I8)=0,"",$F8/$I8)
F9: =IF($D9="","",MAX(0,$D9-$E9)) | G9: =IF(N($D9)=0,"",MIN(1,$E9/$D9)) | I9: =IF($H9="","",MAX(0,DATEDIF(TODAY(),$H9,"M"))) | J9: =IF(N($I9)=0,"",$F9/$I9)
F10: =IF($D10="","",MAX(0,$D10-$E10)) | G10: =IF(N($D10)=0,"",MIN(1,$E10/$D10)) | I10: =IF($H10="","",MAX(0,DATEDIF(TODAY(),$H10,"M"))) | J10: =IF(N($I10)=0,"",$F10/$I10)
F11: =IF($D11="","",MAX(0,$D11-$E11)) | G11: =IF(N($D11)=0,"",MIN(1,$E11/$D11)) | I11: =IF($H11="","",MAX(0,DATEDIF(TODAY(),$H11,"M"))) | J11: =IF(N($I11)=0,"",$F11/$I11)
F12: =IF($D12="","",MAX(0,$D12-$E12)) | G12: =IF(N($D12)=0,"",MIN(1,$E12/$D12)) | I12: =IF($H12="","",MAX(0,DATEDIF(TODAY(),$H12,"M"))) | J12: =IF(N($I12)=0,"",$F12/$I12)
F13: =IF($D13="","",MAX(0,$D13-$E13)) | G13: =IF(N($D13)=0,"",MIN(1,$E13/$D13)) | I13: =IF($H13="","",MAX(0,DATEDIF(TODAY(),$H13,"M"))) | J13: =IF(N($I13)=0,"",$F13/$I13)
F14: =IF($D14="","",MAX(0,$D14-$E14)) | G14: =IF(N($D14)=0,"",MIN(1,$E14/$D14)) | I14: =IF($H14="","",MAX(0,DATEDIF(TODAY(),$H14,"M"))) | J14: =IF(N($I14)=0,"",$F14/$I14)
F15: =IF($D15="","",MAX(0,$D15-$E15)) | G15: =IF(N($D15)=0,"",MIN(1,$E15/$D15)) | I15: =IF($H15="","",MAX(0,DATEDIF(TODAY(),$H15,"M"))) | J15: =IF(N($I15)=0,"",$F15/$I15)
F16: =IF($D16="","",MAX(0,$D16-$E16)) | G16: =IF(N($D16)=0,"",MIN(1,$E16/$D16)) | I16: =IF($H16="","",MAX(0,DATEDIF(TODAY(),$H16,"M"))) | J16: =IF(N($I16)=0,"",$F16/$I16)
... F24: =IF($D24="","",MAX(0,$D24-$E24)) | G24: =IF(N($D24)=0,"",MIN(1,$E24/$D24)) | I24: =IF($H24="","",MAX(0,DATEDIF(TODAY(),$H24,"M"))) | J24: =IF(N($I24)=0,"",$F24/$I24)

Sheet Assinaturas
A1: ASSINATURAS · o dinheiro que sai sozinho
A2: Tudo que debita sem você aprovar. A coluna 'Custo no ano' costuma doer — é pra doer mesmo.
A4: Serviço | B4: Frente | C4: Pra que serve | D4: Valor cobrado | E4: Frequência | F4: Dia da cobrança | G4: Custo no mês | H4: Custo no ano | I4: Cartão | J4: Ativa?
G5: =IF($D5="","",$D5/IFS($E5="Mensal",1,$E5="Trimestral",3,$E5="Semestral",6,$E5="Anual",12)) | H5: =IF($G5="","",$G5*12)
G6: =IF($D6="","",$D6/IFS($E6="Mensal",1,$E6="Trimestral",3,$E6="Semestral",6,$E6="Anual",12)) | H6: =IF($G6="","",$G6*12)
G7: =IF($D7="","",$D7/IFS($E7="Mensal",1,$E7="Trimestral",3,$E7="Semestral",6,$E7="Anual",12)) | H7: =IF($G7="","",$G7*12)
G8: =IF($D8="","",$D8/IFS($E8="Mensal",1,$E8="Trimestral",3,$E8="Semestral",6,$E8="Anual",12)) | H8: =IF($G8="","",$G8*12)
G9: =IF($D9="","",$D9/IFS($E9="Mensal",1,$E9="Trimestral",3,$E9="Semestral",6,$E9="Anual",12)) | H9: =IF($G9="","",$G9*12)
G10: =IF($D10="","",$D10/IFS($E10="Mensal",1,$E10="Trimestral",3,$E10="Semestral",6,$E10="Anual",12)) | H10: =IF($G10="","",$G10*12)
G11: =IF($D11="","",$D11/IFS($E11="Mensal",1,$E11="Trimestral",3,$E11="Semestral",6,$E11="Anual",12)) | H11: =IF($G11="","",$G11*12)
G12: =IF($D12="","",$D12/IFS($E12="Mensal",1,$E12="Trimestral",3,$E12="Semestral",6,$E12="Anual",12)) | H12: =IF($G12="","",$G12*12)
G13: =IF($D13="","",$D13/IFS($E13="Mensal",1,$E13="Trimestral",3,$E13="Semestral",6,$E13="Anual",12)) | H13: =IF($G13="","",$G13*12)
G14: =IF($D14="","",$D14/IFS($E14="Mensal",1,$E14="Trimestral",3,$E14="Semestral",6,$E14="Anual",12)) | H14: =IF($G14="","",$G14*12)
G15: =IF($D15="","",$D15/IFS($E15="Mensal",1,$E15="Trimestral",3,$E15="Semestral",6,$E15="Anual",12)) | H15: =IF($G15="","",$G15*12)
G16: =IF($D16="","",$D16/IFS($E16="Mensal",1,$E16="Trimestral",3,$E16="Semestral",6,$E16="Anual",12)) | H16: =IF($G16="","",$G16*12)
... G34: =IF($D34="","",$D34/IFS($E34="Mensal",1,$E34="Trimestral",3,$E34="Semestral",6,$E34="Anual",12)) | H34: =IF($G34="","",$G34*12)
A36: SANGRIA (só as assinaturas ativas) | G36: =SUMIFS(G5:G34,J5:J34,"Sim") | H36: =SUMIFS(H5:H34,J5:J34,"Sim")

Sheet Estratégias
A1: ESTRATÉGIAS · fazer dinheiro e fazer o dinheiro render
A2: Cada linha é uma aposta. Payback diz em quantos meses ela se paga. Revise no dia 1 do mês.
A4: Estratégia | B4: Frente | C4: Tipo | D4: O que precisa acontecer | E4: Investimento inicial | F4: Custo por mês | G4: Retorno esperado / mês | H4: Lucro líquido / mês | I4: Payback (meses) | J4: Esforço | K4: Status | L4: Próxima ação
H5: =IF($G5="","",$G5-$F5) | I5: =IF(N($H5)<=0,"",$E5/$H5)
H6: =IF($G6="","",$G6-$F6) | I6: =IF(N($H6)<=0,"",$E6/$H6)
H7: =IF($G7="","",$G7-$F7) | I7: =IF(N($H7)<=0,"",$E7/$H7)
H8: =IF($G8="","",$G8-$F8) | I8: =IF(N($H8)<=0,"",$E8/$H8)
H9: =IF($G9="","",$G9-$F9) | I9: =IF(N($H9)<=0,"",$E9/$H9)
H10: =IF($G10="","",$G10-$F10) | I10: =IF(N($H10)<=0,"",$E10/$H10)
H11: =IF($G11="","",$G11-$F11) | I11: =IF(N($H11)<=0,"",$E11/$H11)
H12: =IF($G12="","",$G12-$F12) | I12: =IF(N($H12)<=0,"",$E12/$H12)
H13: =IF($G13="","",$G13-$F13) | I13: =IF(N($H13)<=0,"",$E13/$H13)
H14: =IF($G14="","",$G14-$F14) | I14: =IF(N($H14)<=0,"",$E14/$H14)
H15: =IF($G15="","",$G15-$F15) | I15: =IF(N($H15)<=0,"",$E15/$H15)
H16: =IF($G16="","",$G16-$F16) | I16: =IF(N($H16)<=0,"",$E16/$H16)
... H29: =IF($G29="","",$G29-$F29) | I29: =IF(N($H29)<=0,"",$E29/$H29)
A31: RETORNO LÍQUIDO / MÊS (só as estratégias ativas) | H31: =SUMIFS(H5:H29,K5:K29,"Ativo")
A32: RETORNO LÍQUIDO / MÊS (se tudo que está planejado rodar) | H32: =SUM(H5:H29)

Sheet Listas
A1: LISTAS · as opções dos menus suspensos
A2: Edite aqui e os menus de todas as abas mudam junto. Não apague nem reordene as colunas.
A4: Frente | B4: Tipo | C4: Categoria | D4: Forma de pagamento | E4: Tipo de patrimônio | F4: Frequência | G4: Status | H4: Tipo de estratégia
A5: Pessoal | B5: Entrada | C5: Moradia | D5: Dinheiro | E5: Conta corrente | F5: Mensal | G5: Ativo | H5: Renda ativa
A6: Clean Touch | B6: Saída | C6: Alimentação | D6: Débito | E6: Poupança | F6: Trimestral | G6: Pausado | H6: Renda passiva
A7: Internet | C7: Transporte | D7: Crédito | E7: Reserva de emergência | F7: Semestral | G7: Encerrado | H7: Fazer render (investir)
C8: Saúde | D8: Pix / Transferência | E8: Investimento | F8: Anual | G8: Planejado | H8: Cortar custo
C9: Educação | D9: Boleto | E9: Cripto | G9: Em teste | H9: Escalar o que já existe
C10: Lazer | D10: Zelle | E10: Imóvel
C11: Assinaturas | D11: PayPal | E11: Veículo
C12: Impostos e taxas | D12: Stripe | E12: Equipamento
C13: Marketing | D13: Cheque | E13: Recebível
C14: Fornecedores | D14: Débito automático | E14: Outro
C15: Ferramentas e software
C16: Equipamentos
C17: Salários e pró-labore
C18: Serviços profissionais
C19: Viagem
C20: Tarifas bancárias
C21: Cartão - pagamento de fatura
C22: Empréstimo / parcelamento
C23: Aporte investimento
C24: Resgate investimento
C25: Transferência entre contas
C26: Vendas / serviços
... C29: Outras saídas
